pylatlon/VERSION
pylatlon/__init__.py
pylatlon/pylatlon.py
pylatlon-0.0.4.dist-info/LICENSE
pylatlon-0.0.4.dist-info/METADATA
pylatlon-0.0.4.dist-info/WHEEL
pylatlon-0.0.4.dist-info/top_level.txt
pylatlon-0.0.4.dist-info/RECORD
