Metadata-Version: 2.1
Name: pylatlon
Version: 0.0.4
Summary: Tools to handle geographic positions (parsing, gui input)
Home-page: https://github.com/MarineDataTools/pylatlon
Author: Peter Holtermann
Author-email: peter.holtermann@io-warnemuende.de
License: GPLv03
Platform: UNKNOWN
Requires-Dist: pyproj
